odoo/addons/website_sale_block_partner/README.rst
odoo/addons/website_sale_block_partner/__init__.py
odoo/addons/website_sale_block_partner/__manifest__.py
odoo/addons/website_sale_block_partner/controllers/__init__.py
odoo/addons/website_sale_block_partner/controllers/website_sale.py
odoo/addons/website_sale_block_partner/i18n/es.po
odoo/addons/website_sale_block_partner/i18n/website_sale_block_partner.pot
odoo/addons/website_sale_block_partner/models/__init__.py
odoo/addons/website_sale_block_partner/models/account_move.py
odoo/addons/website_sale_block_partner/models/res_partner.py
odoo/addons/website_sale_block_partner/models/sale_order.py
odoo/addons/website_sale_block_partner/readme/CONTRIBUTORS.md
odoo/addons/website_sale_block_partner/readme/DESCRIPTION.md
odoo/addons/website_sale_block_partner/readme/USAGE.md
odoo/addons/website_sale_block_partner/static/description/icon.png
odoo/addons/website_sale_block_partner/static/description/index.html
odoo/addons/website_sale_block_partner/tests/__init__.py
odoo/addons/website_sale_block_partner/tests/test_block_partner.py
odoo/addons/website_sale_block_partner/views/account_move_views.xml
odoo/addons/website_sale_block_partner/views/res_partner_views.xml
odoo/addons/website_sale_block_partner/views/sale_order_views.xml
odoo/addons/website_sale_block_partner/views/templates.xml
odoo_addon_website_sale_block_partner-15.0.1.0.0.2.dist-info/METADATA
odoo_addon_website_sale_block_partner-15.0.1.0.0.2.dist-info/WHEEL
odoo_addon_website_sale_block_partner-15.0.1.0.0.2.dist-info/top_level.txt
odoo_addon_website_sale_block_partner-15.0.1.0.0.2.dist-info/RECORD
